odoo10_addon_business_requirement_deliverable_project_task_categ-10.0.1.0.0-py2.7-nspkg.pth
odoo/addons/business_requirement_deliverable_project_task_categ/README.rst
odoo/addons/business_requirement_deliverable_project_task_categ/__init__.py
odoo/addons/business_requirement_deliverable_project_task_categ/__manifest__.py
odoo/addons/business_requirement_deliverable_project_task_categ/data/business_requirement_deliverable_project_task_categ_demo.xml
odoo/addons/business_requirement_deliverable_project_task_categ/i18n/sl.po
odoo/addons/business_requirement_deliverable_project_task_categ/models/__init__.py
odoo/addons/business_requirement_deliverable_project_task_categ/models/business_requirement_resource.py
odoo/addons/business_requirement_deliverable_project_task_categ/static/description/icon.png
odoo/addons/business_requirement_deliverable_project_task_categ/static/img/bus_req_category.png
odoo/addons/business_requirement_deliverable_project_task_categ/views/business_requirement_deliverable.xml
odoo/addons/business_requirement_deliverable_project_task_categ/wizard/__init__.py
odoo/addons/business_requirement_deliverable_project_task_categ/wizard/generate_projects.py
odoo10_addon_business_requirement_deliverable_project_task_categ-10.0.1.0.0.dist-info/DESCRIPTION.rst
odoo10_addon_business_requirement_deliverable_project_task_categ-10.0.1.0.0.dist-info/METADATA
odoo10_addon_business_requirement_deliverable_project_task_categ-10.0.1.0.0.dist-info/RECORD
odoo10_addon_business_requirement_deliverable_project_task_categ-10.0.1.0.0.dist-info/WHEEL
odoo10_addon_business_requirement_deliverable_project_task_categ-10.0.1.0.0.dist-info/metadata.json
odoo10_addon_business_requirement_deliverable_project_task_categ-10.0.1.0.0.dist-info/namespace_packages.txt
odoo10_addon_business_requirement_deliverable_project_task_categ-10.0.1.0.0.dist-info/top_level.txt
